marker_web/__init__.py
marker_web/__main__.py
marker_web/auth.py
marker_web/server.py
marker_web/explorer_server/__init__.py
marker_web/explorer_server/favorites.py
marker_web/explorer_server/routes.py
marker_web/gui/favicon.ico
marker_web/gui/index.html
marker_web/gui/css/app.465a2795.css
marker_web/gui/css/chunk-vendors.5521d432.css
marker_web/gui/js/app.6f71d4a6.js
marker_web/gui/js/app.6f71d4a6.js.map
marker_web/gui/js/chunk-vendors.0e17afb9.js
marker_web/gui/js/chunk-vendors.0e17afb9.js.map
marker_web/marker_server/__init__.py
marker_web/marker_server/console.py
marker_web/marker_server/jobs.py
marker_web/marker_server/routes.py
marker_web/marker_server/utils.py
marker_web-1.1.2.dist-info/METADATA
marker_web-1.1.2.dist-info/WHEEL
marker_web-1.1.2.dist-info/entry_points.txt
marker_web-1.1.2.dist-info/top_level.txt
marker_web-1.1.2.dist-info/RECORD
